setup.py
bin/check_mni_reg
bin/recon_movie
bin/recon_process_stats
bin/recon_qc
bin/recon_status
bin/ts_movie
bin/warp_qc
moss/__init__.py
moss/design.py
moss/eyelink.py
moss/freesurfer.py
moss/glm.py
moss/locator.py
moss/misc.py
moss/mosaic.py
moss/plots.py
moss/plotting.py
moss/statistical.py
moss.egg-info/PKG-INFO
moss.egg-info/SOURCES.txt
moss.egg-info/dependency_links.txt
moss.egg-info/top_level.txt
moss/external/__init__.py
moss/external/bunch.py
moss/external/mvpasurf.py
moss/psychophys/__init__.py
moss/psychophys/models.py
moss/psychophys/params.py
moss/psychophys/visualization.py
moss/tests/__init__.py
moss/tests/test_design.py
moss/tests/test_glm.py
moss/tests/test_locator.py
moss/tests/test_misc.py
moss/tests/test_mosaic.py
moss/tests/test_statistical.py