Metadata-Version: 1.1
Name: moss
Version: 0.5
Summary: Moss: statistical utilities for cognitive neuroscience.
Home-page: UNKNOWN
Author: Michael Waskom
Author-email: mwaskom@nyu.edu
License: BSD (3-clause)
Download-URL: https://github.com/mwaskom/moss
Platform: UNKNOWN
Classifier: Intended Audience :: Science/Research
Classifier: Programming Language :: Python
Classifier: License :: OSI Approved
Classifier: Topic :: Scientific/Engineering
Classifier: Operating System :: POSIX
Classifier: Operating System :: Unix
Classifier: Operating System :: MacOS
